backup_original/__init__.py
backup_original/cli.py
backup_original/converter.py
backup_original/cookie_manager.py
backup_original/downloader.py
backup_original/extractor.py
backup_original/main.py
backup_original/main_logic.py
backup_original/proxy_manager.py
backup_original/requirements.txt
backup_original/setup.py
backup_original/utils.py
backup_original/bili_downloader/__init__.py
backup_original/bili_downloader/cli.py
backup_original/bili_downloader/main_logic.py
backup_original/src/__init__.py
backup_original/src/converter.py
backup_original/src/cookie_manager.py
backup_original/src/downloader.py
backup_original/src/extractor.py
backup_original/src/proxy_manager.py
backup_original/src/utils.py
bili_downloader/__init__.py
bili_downloader/cli.py
bili_downloader/main_logic.py
src/__init__.py
src/converter.py
src/cookie_manager.py
src/downloader.py
src/extractor.py
src/proxy_manager.py
src/ui.py
src/utils.py
bili_downloader-1.0.2.dist-info/METADATA
bili_downloader-1.0.2.dist-info/WHEEL
bili_downloader-1.0.2.dist-info/entry_points.txt
bili_downloader-1.0.2.dist-info/top_level.txt
bili_downloader-1.0.2.dist-info/RECORD
