Metadata-Version: 2.4
Name: bili-downloader
Version: 1.0.2
Summary: Bilibili视频下载器 - 类似yt-dlp的B站视频下载工具
Home-page: https://github.com/your-username/bili-downloader
Author: BiliDownloader Team
Author-email: 
Project-URL: Bug Reports, https://github.com/your-username/bili-downloader/issues
Project-URL: Source, https://github.com/your-username/bili-downloader
Project-URL: Documentation, https://github.com/your-username/bili-downloader/blob/main/README.md
Keywords: bilibili video downloader youtube-dl yt-dlp
Classifier: Development Status :: 4 - Beta
Classifier: Intended Audience :: End Users/Desktop
Classifier: License :: OSI Approved :: MIT License
Classifier: Operating System :: OS Independent
Classifier: Programming Language :: Python :: 3
Classifier: Programming Language :: Python :: 3.7
Classifier: Programming Language :: Python :: 3.8
Classifier: Programming Language :: Python :: 3.9
Classifier: Programming Language :: Python :: 3.10
Classifier: Programming Language :: Python :: 3.11
Classifier: Topic :: Multimedia :: Video
Classifier: Topic :: Internet :: WWW/HTTP
Requires-Python: >=3.7
Requires-Dist: requests>=2.31.0
Requires-Dist: beautifulsoup4>=4.12.0
Requires-Dist: lxml>=4.9.0
Requires-Dist: rich>=13.0.0
Dynamic: author
Dynamic: classifier
Dynamic: description
Dynamic: description-content-type
Dynamic: home-page
Dynamic: keywords
Dynamic: project-url
Dynamic: requires-dist
Dynamic: requires-python
Dynamic: summary
